ublox_gps/__init__.py
ublox_gps/core.py
ublox_gps/sfeSpiWrapper.py
ublox_gps/sparkfun_predefines.py
ublox_gps/ublox_gps.py
sparkfun_ublox_gps_remow-1.1.4.dist-info/LICENSE
sparkfun_ublox_gps_remow-1.1.4.dist-info/METADATA
sparkfun_ublox_gps_remow-1.1.4.dist-info/WHEEL
sparkfun_ublox_gps_remow-1.1.4.dist-info/top_level.txt
sparkfun_ublox_gps_remow-1.1.4.dist-info/RECORD
