Metadata-Version: 2.2
Name: sparkfun_ublox_gps_remow
Version: 1.1.4
Summary: SparkFun Electronics Python Package for u-blox GPS modules modified for the ReMow project.
Home-page: https://www.sparkfun.com/gps
Author: Dali Basor
Author-email: basordali@gmail.com
License: GPL GNU 3.0
Keywords: electronics,maker,gps
Classifier: Development Status :: 5 - Production/Stable
Classifier: Intended Audience :: Developers
Classifier: Topic :: Software Development :: Build Tools
Classifier: License :: OSI Approved :: MIT License
Classifier: Programming Language :: Python :: 3.5
Classifier: Programming Language :: Python :: 3.6
Classifier: Programming Language :: Python :: 3.7
Classifier: Programming Language :: Python :: 3.8
License-File: LICENSE
Dynamic: author
Dynamic: author-email
Dynamic: classifier
Dynamic: description
Dynamic: home-page
Dynamic: keywords
Dynamic: license
Dynamic: summary
